setup.py
bin/lldplogger
lldpy/__init__.py
lldpy/liblldpctl.py
lldpy.egg-info/PKG-INFO
lldpy.egg-info/SOURCES.txt
lldpy.egg-info/dependency_links.txt
lldpy.egg-info/requires.txt
lldpy.egg-info/top_level.txt