Metadata-Version: 1.1
Name: lldpy
Version: 0.0.3
Summary: Python wrapper for lldpctl (http://vincentbernat.github.io/lldpd/)
Home-page: https://github.com/jta/lldpy
Author: João Taveira Araújo
Author-email: joao.taveira@gmail.com
License: MIT
Platform: any
Classifier: Development Status :: 4 - Beta
Classifier: Intended Audience :: Developers
Classifier: License :: OSI Approved :: MIT License
Classifier: Programming Language :: Python :: 2.5
Classifier: Programming Language :: Python :: 2.6
Classifier: Programming Language :: Python :: 2.7
Classifier: Programming Language :: Python :: 3
Classifier: Programming Language :: Python :: 3.2
Classifier: Programming Language :: Python :: 3.3
